dic_capture/__init__.py
dic_capture/config.py
dic_capture/gui.py
dic_capture/post_install.py
dic_capture/run.py
dic_capture-0.0.2.dist-info/METADATA
dic_capture-0.0.2.dist-info/WHEEL
dic_capture-0.0.2.dist-info/top_level.txt
dic_capture-0.0.2.dist-info/RECORD
