Metadata-Version: 2.1
Name: dic-capture
Version: 0.0.2
Classifier: Programming Language :: Python :: 3
Classifier: License :: OSI Approved :: MIT License
Classifier: Operating System :: OS Independent
Requires-Python: >=3.6
Requires-Dist: bitarray ==2.6.0
Requires-Dist: contourpy ==1.0.5
Requires-Dist: cycler ==0.11.0
Requires-Dist: easygui ==0.98.3
Requires-Dist: fonttools ==4.38.0
Requires-Dist: future ==0.18.2
Requires-Dist: imageio ==2.22.2
Requires-Dist: iso8601 ==1.1.0
Requires-Dist: kiwisolver ==1.4.4
Requires-Dist: matplotlib ==3.6.1
Requires-Dist: networkx ==2.8.7
Requires-Dist: numpy ==1.23.4
Requires-Dist: opencv-python ==4.6.0.66
Requires-Dist: packaging ==21.3
Requires-Dist: pandas ==2.0.0
Requires-Dist: Pillow ==9.2.0
Requires-Dist: pyFirmata ==1.1.0
Requires-Dist: pyparsing ==3.0.9
Requires-Dist: pyperclip ==1.8.2
Requires-Dist: pyserial ==3.5
Requires-Dist: python-dateutil ==2.8.2
Requires-Dist: pytz ==2023.3
Requires-Dist: PyWavelets ==1.4.1
Requires-Dist: PyYAML ==6.0
Requires-Dist: scikit-image ==0.19.3
Requires-Dist: scipy ==1.9.3
Requires-Dist: six ==1.16.0
Requires-Dist: tifffile ==2022.10.10
Requires-Dist: tzdata ==2023.3
Requires-Dist: ttkthemes ~=3.2.2
